alice_types/__init__.py
alice_types/mixin.py
alice_types/validators.py
alice_types/request/__init__.py
alice_types/request/entity.py
alice_types/request/intents.py
alice_types/request/interfaces.py
alice_types/request/markup.py
alice_types/request/meta.py
alice_types/request/nlu.py
alice_types/request/session.py
alice_types/request/slots.py
alice_types/request/state.py
alice_types/request/type/__init__.py
alice_types/request/type/alice.py
alice_types/request/type/audio.py
alice_types/request/type/button.py
alice_types/request/type/purchase.py
alice_types/request/type/show.py
alice_types/request/type/simple.py
alice_types/response/__init__.py
alice_types/response/analytics.py
alice_types/response/buttons.py
alice_types/response/cards/__init__.py
alice_types/response/cards/base.py
alice_types/response/cards/bigimage.py
alice_types/response/cards/gallery.py
alice_types/response/cards/itemslist.py
alice_types/response/directives/__init__.py
alice_types/response/directives/account.py
alice_types/response/directives/audio.py
alice_types/response/directives/main.py
alice_types/response/type/__init__.py
alice_types/response/type/alice.py
alice_types/response/type/base.py
alice_types/response/type/show.py
alice_types-1.0.1.dist-info/METADATA
alice_types-1.0.1.dist-info/WHEEL
alice_types-1.0.1.dist-info/top_level.txt
alice_types-1.0.1.dist-info/RECORD
