Metadata-Version: 2.1
Name: alice-types
Version: 1.0.1
Summary: Pydantic модели для протокола Алисы.
Author-email: LazyDeus <dimaprodeus@yandex.ru>
Project-URL: Homepage, https://github.com/Demetrous-fd/alice_types
Project-URL: Bug Tracker, https://github.com/Demetrous-fd/alice_types/issues
Classifier: Programming Language :: Python :: 3 :: Only
Classifier: Programming Language :: Python :: 3.9
Classifier: Programming Language :: Python :: 3.10
Classifier: Programming Language :: Python :: 3.11
Classifier: Programming Language :: Python :: 3.12
Classifier: License :: OSI Approved :: MIT License
Classifier: Operating System :: OS Independent
Requires-Python: >=3.9
Requires-Dist: pydantic <3.0.0,>=2.5.2
Requires-Dist: orjson >=3.9.10
Requires-Dist: pytz >=2023.3.post1
Requires-Dist: python-dateutil <3.0.0,>=2.8.2
